tidepool_data_science_metrics/__init__.py
tidepool_data_science_metrics/common/__init__.py
tidepool_data_science_metrics/common/common.py
tidepool_data_science_metrics/glucose/__init__.py
tidepool_data_science_metrics/glucose/glucose.py
tidepool_data_science_metrics/insulin/__init__.py
tidepool_data_science_metrics/insulin/insulin.py
Tidepool_Data_Science_Metrics-0.1.1.dist-info/LICENSE
Tidepool_Data_Science_Metrics-0.1.1.dist-info/METADATA
Tidepool_Data_Science_Metrics-0.1.1.dist-info/WHEEL
Tidepool_Data_Science_Metrics-0.1.1.dist-info/top_level.txt
Tidepool_Data_Science_Metrics-0.1.1.dist-info/RECORD
