Metadata-Version: 2.1
Name: Tidepool-Data-Science-Metrics
Version: 0.1.1
Summary: Set of functions to produce common metrics used in Data Science at Tidepool.
Home-page: https://github.com/tidepool-org/data-science-metrics
Author: Russ Wilson and Ed Nykaza
Author-email: ed@tidepool.org
License: UNKNOWN
Download-URL: https://github.com/tidepool-org/data-science-metrics/tarball/v0.1.1
Platform: UNKNOWN
Classifier: Development Status :: 3 - Alpha
Classifier: Intended Audience :: Developers
Classifier: License :: OSI Approved :: BSD License
Classifier: Programming Language :: Python :: 3.6
Classifier: Programming Language :: Python :: 3.7
Requires-Dist: numpy (==1.18.1)
Requires-Dist: pandas (==1.0.1)
